aiogopro/__init__.py
aiogopro/camera.py
aiogopro/client.py
aiogopro/constants.py
aiogopro/errors.py
aiogopro/infos.py
aiogopro/types.py
aiogopro/utils.py
aiogopro-0.0.1a1.dist-info/LICENSE
aiogopro-0.0.1a1.dist-info/METADATA
aiogopro-0.0.1a1.dist-info/WHEEL
aiogopro-0.0.1a1.dist-info/top_level.txt
aiogopro-0.0.1a1.dist-info/RECORD
