Metadata-Version: 2.1
Name: aiogopro
Version: 0.0.1a1
Summary: some kind of asyncio library for GoPro
Home-page: http://github.com/kmpm/py-aiogopro
Author: Peter Magnusson
Author-email: peter@birchroad.net
License: MIT
Platform: UNKNOWN
Requires-Dist: aiohttp (==3.4.4)
